Metadata-Version: 1.0
Name: BaiduYuyin
Version: 0.1.1
Summary: Library for performing speech recognition with Baidu Speech Recognition API.
Home-page: https://github.com/wwj718/PyBaiduYuyin
Author: Changxu Wang
Author-email: wuwenjie718@gmail.com
License: BSD
Keywords: baidu voice service
Platform: UNKNOWN
